pyfluidsynth.py
pyFluidSynth_musikla-1.3.3.dist-info/LICENSE
pyFluidSynth_musikla-1.3.3.dist-info/METADATA
pyFluidSynth_musikla-1.3.3.dist-info/WHEEL
pyFluidSynth_musikla-1.3.3.dist-info/top_level.txt
pyFluidSynth_musikla-1.3.3.dist-info/RECORD
