Metadata-Version: 2.1
Name: pyFluidSynth-musikla
Version: 1.3.3
Summary: Python bindings for FluidSynth, a MIDI synthesizer that uses SoundFont instruments
Home-page: https://github.com/pedromsilvapt/pyfluidsynth
Author: Nathan Whitehead
Author-email: nwhitehe@gmail.com
License-File: LICENSE
Requires-Dist: future
Requires-Dist: numpy
